CFML-0.0.3.dist-info/AUTHORS.txt
CFML-0.0.3.dist-info/DELVEWHEEL
CFML-0.0.3.dist-info/LICENSE.txt
CFML-0.0.3.dist-info/METADATA
CFML-0.0.3.dist-info/RECORD
CFML-0.0.3.dist-info/top_level.txt
CFML-0.0.3.dist-info/WHEEL
CFML.libs/.load-order-CFML-0.0.3
CFML.libs/libgcc_s_seh-1.dll
CFML.libs/libquadmath-0.dll
CFML.libs/libwinpthread-1.dll
CFML_api/API_Atom_TypeDef.py
CFML_api/API_Crystallographic_Symmetry.py
CFML_api/API_Crystal_Metrics.py
CFML_api/API_Diffraction_Patterns.py
CFML_api/API_Error_Messages.py
CFML_api/API_IO_Formats.py
CFML_api/API_Reflections_Utilities.py
CFML_api/crysfml_api.pyd
CFML_api/FortranBindedClass.py
CFML_api/PowderPatternSimulation.py
CFML_api/__init__.py
Examples/lowlevelapi_powdergeneration.py
Examples/test_atom_list.py
Examples/test_atom_list_destructor.py
Examples/test_cell.py
Examples/test_cell_destructor.py
Examples/test_diffraction_pattern_destructor.py
Examples/test_error_messages_destructor.py
Examples/test_job_info.py
Examples/test_powder_generation.py
Examples/test_symmetry_groups.py
Examples/test_symmetry_groups_destructor.py
Examples/__init__.py
Examples/Data/calcite.cif
Examples/Data/ponsin.cfl
Examples/Data/Si_Laue.cfl
Examples/Data/SrTiO3.cfl
Examples/Data/SrTiO3.cif
Examples/Data/SrTiO3_jobtype.cfl
Tests/test_crystal_metrics.py
Tests/test_symmetry_groups.py
Tests/__init__.py
