Metadata-Version: 2.1
Name: CFML
Version: 0.0.3
Summary: The Crystallographic Fortran Modules Library (CrysFML) is a set of modules containing procedures of interest in Crystallographic applications.
Author: Juan Rodriguez-Carvajal, Elisa Rebolini, Simon Ward
Author-email: rebolini@ill.fr
License: LGPL
Keywords: crystallography,physics,neutron,diffraction
Platform: UNKNOWN
Classifier: Intended Audience :: Developers
Classifier: License :: OSI Approved :: GNU Lesser General Public License v3 (LGPLv3)
Classifier: Natural Language :: English
Classifier: Programming Language :: Fortran
Classifier: Programming Language :: Python
License-File: LICENSE.txt
License-File: AUTHORS.txt
